<?xml version="1.0"?>
<pklist version="1.0" creator="flexAnalysis 3.4.76.0" shots="240" date="2018-02-02T13:32:04.002+01:00" spectrumid="A5A1E809-C9A1-434F-84F7-28A53261EC40">
<pk>
<absi>603.8398853636995</absi>
<area>4803.781622988571</area>
<ind>720.4659212751612</ind>
<lind>703.0000000000000</lind>
<lmass>2306.687754290956</lmass>
<mass>2314.580797686644</mass>
<meth>2</meth>
<reso>525.3199952702769</reso>
<rind>728.0000000000000</rind>
<rmass>2317.989695767424</rmass>
<s2n>4.497155666168775</s2n>
</pk>
<pk>
<absi>1292.269319405874</absi>
<area>9458.742351979294</area>
<ind>749.2198632900236</ind>
<lind>736.0000000000000</lind>
<lmass>2321.612154007236</lmass>
<mass>2327.604406664136</mass>
<meth>2</meth>
<reso>510.4721358259895</reso>
<rind>759.0000000000000</rind>
<rmass>2332.042485733634</rmass>
<s2n>9.624300137911291</s2n>
</pk>
<pk>
<absi>877.9677269397289</absi>
<area>3456.237031676325</area>
<ind>767.4133219140549</ind>
<lind>760.0000000000000</lind>
<lmass>2332.496509053598</lmass>
<mass>2335.863709089104</mass>
<meth>2</meth>
<reso>1125.916804771004</reso>
<rind>770.0000000000000</rind>
<rmass>2337.039174340832</rmass>
<s2n>6.538749151262477</s2n>
</pk>
<pk>
<absi>1556.218548683678</absi>
<area>10584.26596517011</area>
<ind>781.1008692830255</ind>
<lind>771.0000000000000</lind>
<lmass>2337.493684078490</lmass>
<mass>2342.087106678323</mass>
<meth>2</meth>
<reso>514.3476510247912</reso>
<rind>791.0000000000000</rind>
<rmass>2346.593165008361</rmass>
<s2n>11.59008742821691</s2n>
</pk>
<pk>
<absi>1035.195319277628</absi>
<area>4978.676880860769</area>
<ind>800.6921815960704</ind>
<lind>792.0000000000000</lind>
<lmass>2347.048603364305</lmass>
<mass>2351.009218944644</mass>
<meth>2</meth>
<reso>836.1147596373254</reso>
<rind>804.0000000000000</rind>
<rmass>2352.517312798397</rmass>
<s2n>7.709716778441622</s2n>
</pk>
<pk>
<absi>1219.336749982597</absi>
<area>7360.594300982413</area>
<ind>811.3006084928838</ind>
<lind>805.0000000000000</lind>
<lmass>2352.973326015044</lmass>
<mass>2355.847503785456</mass>
<meth>2</meth>
<reso>647.3507537451933</reso>
<rind>821.0000000000000</rind>
<rmass>2360.275551421807</rmass>
<s2n>9.081127807331329</s2n>
</pk>
<pk>
<absi>783.7230322584042</absi>
<area>3592.062444062536</area>
<ind>841.1941913705050</ind>
<lind>838.0000000000000</lind>
<lmass>2368.046569693976</lmass>
<mass>2369.508120567522</mass>
<meth>2</meth>
<reso>908.0700190034146</reso>
<rind>850.0000000000000</rind>
<rmass>2373.539688699401</rmass>
<s2n>5.778282972403035</s2n>
</pk>
<pk>
<absi>611.7559128473733</absi>
<area>6925.998508061506</area>
<ind>4409.081219058764</ind>
<lind>4401.000000000000</lind>
<lmass>4278.848200201874</lmass>
<mass>4283.820423293650</mass>
<meth>2</meth>
<reso>652.3611936955182</reso>
<rind>4426.000000000000</rind>
<rmass>4294.239591062548</rmass>
<s2n>4.080937828015176</s2n>
</pk>
<pk>
<absi>697.8690385586433</absi>
<area>4381.693288324346</area>
<ind>4915.784435041176</ind>
<lind>4906.000000000000</lind>
<lmass>4595.117428515539</lmass>
<mass>4601.356627246159</mass>
<meth>2</meth>
<reso>1349.838354467870</reso>
<rind>4918.000000000000</rind>
<rmass>4602.770005323452</rmass>
<s2n>4.599171452864870</s2n>
</pk>
<pk>
<absi>793.1776124745288</absi>
<area>3345.765483488574</area>
<ind>4923.494193165549</ind>
<lind>4919.000000000000</lind>
<lmass>4603.408007701715</lmass>
<mass>4606.275859976630</mass>
<meth>2</meth>
<reso>1705.887069372260</reso>
<rind>4926.000000000000</rind>
<rmass>4607.875263434078</rmass>
<s2n>5.227284247885174</s2n>
</pk>
<pk>
<absi>3527.389575392148</absi>
<area>41358.99059671950</area>
<ind>4966.214667228169</ind>
<lind>4951.000000000000</lind>
<lmass>4623.847449435010</lmass>
<mass>4633.581447462983</mass>
<meth>2</meth>
<reso>711.4870427803572</reso>
<rind>4978.000000000000</rind>
<rmass>4641.128476107052</rmass>
<s2n>23.22782051884748</s2n>
</pk>
<pk>
<absi>2717.254307218599</absi>
<area>25945.83398298598</area>
<ind>4987.717380195825</ind>
<lind>4979.000000000000</lind>
<lmass>4641.769133679611</lmass>
<mass>4647.355863674216</mass>
<meth>2</meth>
<reso>855.0197106679734</reso>
<rind>4995.000000000000</rind>
<rmass>4652.025673319582</rmass>
<s2n>17.89308892685100</s2n>
</pk>
<pk>
<absi>7357.452526637110</absi>
<area>79524.96127590847</area>
<ind>5009.710446618436</ind>
<lind>4996.000000000000</lind>
<lmass>4652.667083202428</lmass>
<mass>4661.465561850311</mass>
<meth>2</meth>
<reso>665.5872044909836</reso>
<rind>5022.000000000000</rind>
<rmass>4669.359273199820</rmass>
<s2n>48.44874179956963</s2n>
</pk>
<pk>
<absi>4084.074596962953</absi>
<area>43183.34438487016</area>
<ind>5035.131353423951</ind>
<lind>5023.000000000000</lind>
<lmass>4670.001877933167</lmass>
<mass>4677.801067909664</mass>
<meth>2</meth>
<reso>790.2700566939276</reso>
<rind>5041.000000000000</rind>
<rmass>4681.576330546815</rmass>
<s2n>26.89358509920004</s2n>
</pk>
<pk>
<absi>8157.621409476552</absi>
<area>92792.30851884684</area>
<ind>5053.258831274705</ind>
<lind>5042.000000000000</lind>
<lmass>4682.219776104381</lmass>
<mass>4689.467275043450</mass>
<meth>2</meth>
<reso>643.6125427644523</reso>
<rind>5067.000000000000</rind>
<rmass>4698.320297609862</rmass>
<s2n>53.71784485669225</s2n>
</pk>
<pk>
<absi>5027.088448612031</absi>
<area>52250.19694934567</area>
<ind>5079.398656126536</ind>
<lind>5068.000000000000</lind>
<lmass>4698.964893773671</lmass>
<mass>4706.315550966147</mass>
<meth>2</meth>
<reso>734.3259050987838</reso>
<rind>5086.000000000000</rind>
<rmass>4710.575192197206</rmass>
<s2n>33.10332066277378</s2n>
</pk>
<pk>
<absi>6081.952052287209</absi>
<area>73272.06244393117</area>
<ind>5096.572232081408</ind>
<lind>5087.000000000000</lind>
<lmass>4711.220629192075</lmass>
<mass>4717.401141168842</mass>
<meth>2</meth>
<reso>663.6063424251080</reso>
<rind>5111.000000000000</rind>
<rmass>4726.724393391203</rmass>
<s2n>40.04958558031063</s2n>
</pk>
<pk>
<absi>4033.705096930080</absi>
<area>48321.53230190980</area>
<ind>5123.358502859206</ind>
<lind>5112.000000000000</lind>
<lmass>4727.370936747131</lmass>
<mass>4734.717807401790</mass>
<meth>2</meth>
<reso>717.1976212316183</reso>
<rind>5133.000000000000</rind>
<rmass>4740.958570034094</rmass>
<s2n>26.56190251031061</s2n>
</pk>
<pk>
<absi>3346.712213559048</absi>
<area>38565.22018671462</area>
<ind>5136.814363017242</ind>
<lind>5134.000000000000</lind>
<lmass>4741.606086991887</lmass>
<mass>4743.428672308233</mass>
<meth>2</meth>
<reso>670.9704823912149</reso>
<rind>5156.000000000000</rind>
<rmass>4755.862656522248</rmass>
<s2n>22.03806213158130</s2n>
</pk>
<pk>
<absi>2365.625556425936</absi>
<area>28018.76386997934</area>
<ind>5168.793142515984</ind>
<lind>5157.000000000000</lind>
<lmass>4756.511191340679</lmass>
<mass>4764.162793281973</mass>
<meth>2</meth>
<reso>698.4906876913027</reso>
<rind>5177.000000000000</rind>
<rmass>4769.491181250259</rmass>
<s2n>15.58450051771287</s2n>
</pk>
<pk>
<absi>1767.592458577870</absi>
<area>8739.133466329004</area>
<ind>5187.381210126992</ind>
<lind>5185.000000000000</lind>
<lmass>4774.688133777940</lmass>
<mass>4776.235560266236</mass>
<meth>2</meth>
<reso>1832.437781868220</reso>
<rind>5193.000000000000</rind>
<rmass>4779.887918633961</rmass>
<s2n>11.64471930521039</s2n>
</pk>
<pk>
<absi>1695.998780146880</absi>
<area>23304.23330468293</area>
<ind>5200.365329489683</ind>
<lind>5194.000000000000</lind>
<lmass>4780.538090889256</lmass>
<mass>4784.677688922356</mass>
<meth>2</meth>
<reso>511.0305585948308</reso>
<rind>5218.000000000000</rind>
<rmass>4796.155501595410</rmass>
<s2n>11.17306743471807</s2n>
</pk>
<pk>
<absi>1036.389309832232</absi>
<area>11711.84557646558</area>
<ind>5252.466758078586</ind>
<lind>5244.000000000000</lind>
<lmass>4813.103129203566</lmass>
<mass>4818.628488991060</mass>
<meth>2</meth>
<reso>590.7916665898258</reso>
<rind>5265.000000000000</rind>
<rmass>4826.813437789511</rmass>
<s2n>6.827627344386181</s2n>
</pk>
<pk>
<absi>732.6810155453472</absi>
<area>8953.141609759539</area>
<ind>5302.473792188794</ind>
<lind>5287.000000000000</lind>
<lmass>4841.197551193559</lmass>
<mass>4851.327508790007</mass>
<meth>2</meth>
<reso>716.4834563053464</reso>
<rind>5310.000000000000</rind>
<rmass>4856.258390387825</rmass>
<s2n>4.826827996961718</s2n>
</pk>
<pk>
<absi>797.6098453003715</absi>
<area>8664.957313700175</area>
<ind>5320.881453693650</ind>
<lind>5311.000000000000</lind>
<lmass>4856.913740556091</lmass>
<mass>4863.391932209561</mass>
<meth>2</meth>
<reso>730.0363275111121</reso>
<rind>5331.000000000000</rind>
<rmass>4870.030037721100</rmass>
<s2n>5.254572522371924</s2n>
</pk>
<pk>
<absi>688.6874602111918</absi>
<area>8111.383665929900</area>
<ind>8497.595871854122</ind>
<lind>8486.000000000000</lind>
<lmass>7160.828239979691</lmass>
<mass>7170.060671597268</mass>
<meth>2</meth>
<reso>1047.355582438522</reso>
<rind>8505.000000000000</rind>
<rmass>7175.958824468382</rmass>
<s2n>4.539675210177650</s2n>
</pk>
<pk>
<absi>939.5805793285416</absi>
<area>11044.16733775751</area>
<ind>10150.31336784499</ind>
<lind>10147.00000000000</lind>
<lmass>8543.951893556523</lmass>
<mass>8546.833072227988</mass>
<meth>2</meth>
<reso>1755.007352310047</reso>
<rind>10162.00000000000</rind>
<rmass>8556.999205547632</rmass>
<s2n>7.214798047202001</s2n>
</pk>
<pk>
<absi>1046.931057004527</absi>
<area>14994.60110268072</area>
<ind>10170.28233171526</ind>
<lind>10163.00000000000</lind>
<lmass>8557.869380706579</lmass>
<mass>8564.207620684098</mass>
<meth>2</meth>
<reso>958.4238596940074</reso>
<rind>10182.00000000000</rind>
<rmass>8574.411124783481</rmass>
<s2n>8.039114804851884</s2n>
</pk>
<pk>
<absi>704.1410240322049</absi>
<area>11317.26678631005</area>
<ind>10378.59879557758</ind>
<lind>10358.00000000000</lind>
<lmass>8728.400023826440</lmass>
<mass>8746.512363710890</mass>
<meth>2</meth>
<reso>980.4929194915226</reso>
<rind>10387.00000000000</rind>
<rmass>8753.904865021119</rmass>
<s2n>5.538090236867462</s2n>
</pk>
<pk>
<absi>801.8995797377462</absi>
<area>11681.96860639508</area>
<ind>10443.73575208391</ind>
<lind>10434.00000000000</lind>
<lmass>8795.319411442515</lmass>
<mass>8803.910406299403</mass>
<meth>2</meth>
<reso>1265.567189642508</reso>
<rind>10455.00000000000</rind>
<rmass>8813.855411370229</rmass>
<s2n>6.306964204503752</s2n>
</pk>
<pk>
<absi>637.8665763734942</absi>
<area>3275.952535989056</area>
<ind>10662.97553811591</ind>
<lind>10661.00000000000</lind>
<lmass>8996.720471373292</lmass>
<mass>8998.483245933274</mass>
<meth>2</meth>
<reso>2801.628653099215</reso>
<rind>10667.00000000000</rind>
<rmass>9002.074811980208</rmass>
<s2n>5.095596191561677</s2n>
</pk>
</pklist>
